amoni/__init__.py
amoni/api.py
amoni/cli/__init__.py
amoni/cli/amoni.py
amoni/cli/app.py
amoni/cli/echo.py
amoni/cli/table.py
amoni/cli/theme.py
amoni-0.0.13.dist-info/entry_points.txt
amoni-0.0.13.dist-info/LICENSE
amoni-0.0.13.dist-info/LICENSE.txt
amoni-0.0.13.dist-info/WHEEL
amoni-0.0.13.dist-info/METADATA
amoni-0.0.13.dist-info/RECORD
