Metadata-Version: 2.1
Name: amoni
Version: 0.0.13
Summary: A tool to manage local development of Anvil applications
Author: The Anvilistas Team
Classifier: License :: OSI Approved :: MIT License
Requires-Dist: cookiecutter
Requires-Dist: keyring
Requires-Dist: pygit2
Requires-Dist: python-on-whales
Requires-Dist: pyyaml
Requires-Dist: typer
Project-URL: Home, https://github.com/anvilistas/amoni
